<?xml version="1.0" encoding="utf-8"?>
<Document>
  <Engineering version="V17" />
  <DocumentInfo>
    <Created>2023-05-07T12:12:21.9941394Z</Created>
    <ExportSetting>WithDefaults</ExportSetting>
    <InstalledProducts>
      <Product>
        <DisplayName>Totally Integrated Automation Portal</DisplayName>
        <DisplayVersion>V17</DisplayVersion>
      </Product>
      <OptionPackage>
        <DisplayName>TIA Portal Openness</DisplayName>
        <DisplayVersion>V17</DisplayVersion>
      </OptionPackage>
      <OptionPackage>
        <DisplayName>TIA Portal Version Control Interface</DisplayName>
        <DisplayVersion>V17</DisplayVersion>
      </OptionPackage>
      <OptionPackage>
        <DisplayName>TIA Portal Test Suite Advanced</DisplayName>
        <DisplayVersion>V17</DisplayVersion>
      </OptionPackage>
      <Product>
        <DisplayName>STEP 7 Professional</DisplayName>
        <DisplayVersion>V17</DisplayVersion>
      </Product>
      <OptionPackage>
        <DisplayName>SIMATIC Energy Suite</DisplayName>
        <DisplayVersion>V17</DisplayVersion>
      </OptionPackage>
      <OptionPackage>
        <DisplayName>STEP 7 Safety</DisplayName>
        <DisplayVersion>V17</DisplayVersion>
      </OptionPackage>
      <Product>
        <DisplayName>WinCC Professional</DisplayName>
        <DisplayVersion>V17</DisplayVersion>
      </Product>
    </InstalledProducts>
  </DocumentInfo>
  <SW.Blocks.GlobalDB ID="0">
    <AttributeList>
      <AutoNumber>true</AutoNumber>
      <HeaderAuthor />
      <HeaderFamily />
      <HeaderName />
      <HeaderVersion>0.1</HeaderVersion>
      <Interface><Sections xmlns="http://www.siemens.com/automation/Openness/SW/Interface/v5">
  <Section Name="Static">
    <Member Name="Start" Datatype="Bool" Remanence="NonRetain" Accessibility="Public"><AttributeList><BooleanAttribute Name="ExternalAccessible" SystemDefined="true">true</BooleanAttribute><BooleanAttribute Name="ExternalVisible" SystemDefined="true">true</BooleanAttribute><BooleanAttribute Name="ExternalWritable" SystemDefined="true">true</BooleanAttribute><BooleanAttribute Name="SetPoint" SystemDefined="true">false</BooleanAttribute></AttributeList></Member>
    <Member Name="Stop" Datatype="Bool" Remanence="NonRetain" Accessibility="Public"><AttributeList><BooleanAttribute Name="ExternalAccessible" SystemDefined="true">true</BooleanAttribute><BooleanAttribute Name="ExternalVisible" SystemDefined="true">true</BooleanAttribute><BooleanAttribute Name="ExternalWritable" SystemDefined="true">true</BooleanAttribute><BooleanAttribute Name="SetPoint" SystemDefined="true">false</BooleanAttribute></AttributeList></Member>
    <Member Name="Empty" Datatype="Bool" Remanence="NonRetain" Accessibility="Public"><AttributeList><BooleanAttribute Name="ExternalAccessible" SystemDefined="true">true</BooleanAttribute><BooleanAttribute Name="ExternalVisible" SystemDefined="true">true</BooleanAttribute><BooleanAttribute Name="ExternalWritable" SystemDefined="true">true</BooleanAttribute><BooleanAttribute Name="SetPoint" SystemDefined="true">false</BooleanAttribute></AttributeList></Member>
    <Member Name="Controller" Datatype="Int" Remanence="NonRetain" Accessibility="Public"><AttributeList><BooleanAttribute Name="ExternalAccessible" SystemDefined="true">true</BooleanAttribute><BooleanAttribute Name="ExternalVisible" SystemDefined="true">true</BooleanAttribute><BooleanAttribute Name="ExternalWritable" SystemDefined="true">true</BooleanAttribute><BooleanAttribute Name="SetPoint" SystemDefined="true">false</BooleanAttribute></AttributeList></Member>
    <Member Name="RandomDisturbance" Datatype="Int" Remanence="NonRetain" Accessibility="Public"><AttributeList><BooleanAttribute Name="ExternalAccessible" SystemDefined="true">true</BooleanAttribute><BooleanAttribute Name="ExternalVisible" SystemDefined="true">true</BooleanAttribute><BooleanAttribute Name="ExternalWritable" SystemDefined="true">true</BooleanAttribute><BooleanAttribute Name="SetPoint" SystemDefined="true">false</BooleanAttribute></AttributeList></Member>
    <Member Name="SetPoint" Datatype="Real" Remanence="NonRetain" Accessibility="Public"><AttributeList><BooleanAttribute Name="ExternalAccessible" SystemDefined="true">true</BooleanAttribute><BooleanAttribute Name="ExternalVisible" SystemDefined="true">true</BooleanAttribute><BooleanAttribute Name="ExternalWritable" SystemDefined="true">true</BooleanAttribute><BooleanAttribute Name="SetPoint" SystemDefined="true">false</BooleanAttribute></AttributeList></Member>
    <Member Name="Outflow" Datatype="Real" Remanence="NonRetain" Accessibility="Public"><AttributeList><BooleanAttribute Name="ExternalAccessible" SystemDefined="true">true</BooleanAttribute><BooleanAttribute Name="ExternalVisible" SystemDefined="true">true</BooleanAttribute><BooleanAttribute Name="ExternalWritable" SystemDefined="true">true</BooleanAttribute><BooleanAttribute Name="SetPoint" SystemDefined="true">false</BooleanAttribute></AttributeList></Member>
    <Member Name="LevelMeterShow" Datatype="Real" Remanence="NonRetain" Accessibility="Public"><AttributeList><BooleanAttribute Name="ExternalAccessible" SystemDefined="true">true</BooleanAttribute><BooleanAttribute Name="ExternalVisible" SystemDefined="true">true</BooleanAttribute><BooleanAttribute Name="ExternalWritable" SystemDefined="true">true</BooleanAttribute><BooleanAttribute Name="SetPoint" SystemDefined="true">false</BooleanAttribute></AttributeList></Member>
    <Member Name="SetPointShow" Datatype="Real" Remanence="NonRetain" Accessibility="Public"><AttributeList><BooleanAttribute Name="ExternalAccessible" SystemDefined="true">true</BooleanAttribute><BooleanAttribute Name="ExternalVisible" SystemDefined="true">true</BooleanAttribute><BooleanAttribute Name="ExternalWritable" SystemDefined="true">true</BooleanAttribute><BooleanAttribute Name="SetPoint" SystemDefined="true">false</BooleanAttribute></AttributeList></Member>
    <Member Name="FillValveShow" Datatype="Real" Remanence="NonRetain" Accessibility="Public"><AttributeList><BooleanAttribute Name="ExternalAccessible" SystemDefined="true">true</BooleanAttribute><BooleanAttribute Name="ExternalVisible" SystemDefined="true">true</BooleanAttribute><BooleanAttribute Name="ExternalWritable" SystemDefined="true">true</BooleanAttribute><BooleanAttribute Name="SetPoint" SystemDefined="true">false</BooleanAttribute></AttributeList></Member>
    <Member Name="TopPump" Datatype="Int" Remanence="NonRetain" Accessibility="Public"><AttributeList><BooleanAttribute Name="ExternalAccessible" SystemDefined="true">true</BooleanAttribute><BooleanAttribute Name="ExternalVisible" SystemDefined="true">true</BooleanAttribute><BooleanAttribute Name="ExternalWritable" SystemDefined="true">true</BooleanAttribute><BooleanAttribute Name="SetPoint" SystemDefined="true">false</BooleanAttribute></AttributeList></Member>
    <Member Name="LowPump" Datatype="Int" Remanence="NonRetain" Accessibility="Public"><AttributeList><BooleanAttribute Name="ExternalAccessible" SystemDefined="true">true</BooleanAttribute><BooleanAttribute Name="ExternalVisible" SystemDefined="true">true</BooleanAttribute><BooleanAttribute Name="ExternalWritable" SystemDefined="true">true</BooleanAttribute><BooleanAttribute Name="SetPoint" SystemDefined="true">false</BooleanAttribute></AttributeList></Member>
    <Member Name="Status" Datatype="Bool" Remanence="NonRetain" Accessibility="Public"><AttributeList><BooleanAttribute Name="ExternalAccessible" SystemDefined="true">true</BooleanAttribute><BooleanAttribute Name="ExternalVisible" SystemDefined="true">true</BooleanAttribute><BooleanAttribute Name="ExternalWritable" SystemDefined="true">true</BooleanAttribute><BooleanAttribute Name="SetPoint" SystemDefined="true">false</BooleanAttribute></AttributeList></Member>
    <Member Name="default" Datatype="Bool" Remanence="NonRetain" Accessibility="Public"><AttributeList><BooleanAttribute Name="ExternalAccessible" SystemDefined="true">true</BooleanAttribute><BooleanAttribute Name="ExternalVisible" SystemDefined="true">true</BooleanAttribute><BooleanAttribute Name="ExternalWritable" SystemDefined="true">true</BooleanAttribute><BooleanAttribute Name="SetPoint" SystemDefined="true">false</BooleanAttribute></AttributeList></Member>
    <Member Name="finish_training" Datatype="Int" Remanence="NonRetain" Accessibility="Public"><AttributeList><BooleanAttribute Name="ExternalAccessible" SystemDefined="true">true</BooleanAttribute><BooleanAttribute Name="ExternalVisible" SystemDefined="true">true</BooleanAttribute><BooleanAttribute Name="ExternalWritable" SystemDefined="true">true</BooleanAttribute><BooleanAttribute Name="SetPoint" SystemDefined="true">false</BooleanAttribute></AttributeList></Member>
    <Member Name="factoryio_connect" Datatype="Bool" Remanence="NonRetain" Accessibility="Public"><AttributeList><BooleanAttribute Name="ExternalAccessible" SystemDefined="true">true</BooleanAttribute><BooleanAttribute Name="ExternalVisible" SystemDefined="true">true</BooleanAttribute><BooleanAttribute Name="ExternalWritable" SystemDefined="true">true</BooleanAttribute><BooleanAttribute Name="SetPoint" SystemDefined="true">false</BooleanAttribute></AttributeList></Member>
  </Section>
</Sections></Interface>
      <IsOnlyStoredInLoadMemory>false</IsOnlyStoredInLoadMemory>
      <IsRetainMemResEnabled>false</IsRetainMemResEnabled>
      <IsWriteProtectedInAS>false</IsWriteProtectedInAS>
      <MemoryLayout>Optimized</MemoryLayout>
      <MemoryReserve>100</MemoryReserve>
      <Name>VisuData</Name>
      <Number>9</Number>
      <ProgrammingLanguage>DB</ProgrammingLanguage>
    </AttributeList>
    <ObjectList>
      <MultilingualText ID="1" CompositionName="Comment">
        <ObjectList>
          <MultilingualTextItem ID="2" CompositionName="Items">
            <AttributeList>
              <Culture>en-US</Culture>
              <Text />
            </AttributeList>
          </MultilingualTextItem>
        </ObjectList>
      </MultilingualText>
      <MultilingualText ID="3" CompositionName="Title">
        <ObjectList>
          <MultilingualTextItem ID="4" CompositionName="Items">
            <AttributeList>
              <Culture>en-US</Culture>
              <Text />
            </AttributeList>
          </MultilingualTextItem>
        </ObjectList>
      </MultilingualText>
    </ObjectList>
  </SW.Blocks.GlobalDB>
</Document>